{
  "data": {
    "ACC": {
      "symbol": "ACC",
      "price": 1350,
      "previousClose": 1359.3,
      "open": 1350,
      "dayHigh": 1353.8,
      "dayLow": 1343,
      "change": -9.3,
      "changePercent": -0.68
    },
    "ADANIENT": {
      "symbol": "ADANIENT",
      "price": 2704,
      "previousClose": 2725,
      "open": 2704,
      "dayHigh": 2720,
      "dayLow": 2685.1,
      "change": -21,
      "changePercent": -0.77
    },
    "ADANIGREEN": {
      "symbol": "ADANIGREEN",
      "price": 1362.1,
      "previousClose": 1377.8,
      "open": 1362.1,
      "dayHigh": 1369,
      "dayLow": 1348.1,
      "change": -15.7,
      "changePercent": -1.14
    },
    "ADANIPORTS": {
      "symbol": "ADANIPORTS",
      "price": 1766,
      "previousClose": 1762.8,
      "open": 1766,
      "dayHigh": 1774.6,
      "dayLow": 1744.3,
      "change": 3.2,
      "changePercent": 0.18
    },
    "ADANIPOWER": {
      "symbol": "ADANIPOWER",
      "price": 219.66,
      "previousClose": 219.09,
      "open": 219.66,
      "dayHigh": 220.25,
      "dayLow": 216.19,
      "change": 0.57,
      "changePercent": 0.26
    },
    "ALKEM": {
      "symbol": "ALKEM",
      "price": 5445.5,
      "previousClose": 5470,
      "open": 5445.5,
      "dayHigh": 5507.5,
      "dayLow": 5422.5,
      "change": -24.5,
      "changePercent": -0.45
    },
    "AMBUJACEM": {
      "symbol": "AMBUJACEM",
      "price": 430,
      "previousClose": 431.7,
      "open": 430,
      "dayHigh": 430.15,
      "dayLow": 425.15,
      "change": -1.7,
      "changePercent": -0.39
    },
    "APOLLOHOSP": {
      "symbol": "APOLLOHOSP",
      "price": 8122,
      "previousClose": 8026,
      "open": 8122,
      "dayHigh": 8129,
      "dayLow": 7814.5,
      "change": 96,
      "changePercent": 1.2
    },
    "ASIANPAINT": {
      "symbol": "ASIANPAINT",
      "price": 2607.4,
      "previousClose": 2600.7,
      "open": 2607.4,
      "dayHigh": 2614,
      "dayLow": 2562,
      "change": 6.7,
      "changePercent": 0.26
    },
    "ATGL": {
      "symbol": "ATGL",
      "price": 610.9,
      "previousClose": 623.3,
      "open": 610.9,
      "dayHigh": 617.95,
      "dayLow": 601.1,
      "change": -12.4,
      "changePercent": -1.99
    },
    "AUROPHARMA": {
      "symbol": "AUROPHARMA",
      "price": 1517.1,
      "previousClose": 1512.8,
      "open": 1517.1,
      "dayHigh": 1539,
      "dayLow": 1505.1,
      "change": 4.3,
      "changePercent": 0.28
    },
    "AXISBANK": {
      "symbol": "AXISBANK",
      "price": 1249.9,
      "previousClose": 1238.3,
      "open": 1249.9,
      "dayHigh": 1251.4,
      "dayLow": 1226.6,
      "change": 11.6,
      "changePercent": 0.94
    },
    "BAJAJ-AUTO": {
      "symbol": "BAJAJ-AUTO",
      "price": 10415,
      "previousClose": 10205,
      "open": 10415,
      "dayHigh": 10435,
      "dayLow": 10078.5,
      "change": 210,
      "changePercent": 2.06
    },
    "BAJAJHLDNG": {
      "symbol": "BAJAJHLDNG",
      "price": 10431,
      "previousClose": 10313,
      "open": 10431,
      "dayHigh": 10445,
      "dayLow": 10171,
      "change": 118,
      "changePercent": 1.14
    },
    "BAJFINANCE": {
      "symbol": "BAJFINANCE",
      "price": 918.1,
      "previousClose": 923.55,
      "open": 918.1,
      "dayHigh": 921.85,
      "dayLow": 908.45,
      "change": -5.45,
      "changePercent": -0.59
    },
    "BAJFINSERV": {
      "symbol": "BAJFINSERV",
      "price": 1773.5,
      "previousClose": 1749.8,
      "open": 1773.5,
      "dayHigh": 1776.5,
      "dayLow": 1726,
      "change": 23.7,
      "changePercent": 1.35
    },
    "BANKBARODA": {
      "symbol": "BANKBARODA",
      "price": 262.05,
      "previousClose": 260.6,
      "open": 262.05,
      "dayHigh": 263.75,
      "dayLow": 256.65,
      "change": 1.45,
      "changePercent": 0.56
    },
    "BANKINDIA": {
      "symbol": "BANKINDIA",
      "price": 137.26,
      "previousClose": 138.64,
      "open": 137.26,
      "dayHigh": 138.55,
      "dayLow": 136.5,
      "change": -1.38,
      "changePercent": -1
    },
    "BDL": {
      "symbol": "BDL",
      "price": 1298.7,
      "previousClose": 1311.8,
      "open": 1298.7,
      "dayHigh": 1299.9,
      "dayLow": 1279.3,
      "change": -13.1,
      "changePercent": -1
    },
    "BEL": {
      "symbol": "BEL",
      "price": 412.15,
      "previousClose": 422.95,
      "open": 412.15,
      "dayHigh": 420,
      "dayLow": 407,
      "change": -10.8,
      "changePercent": -2.55
    },
    "BHARATFORG": {
      "symbol": "BHARATFORG",
      "price": 1876.9,
      "previousClose": 1857.3,
      "open": 1876.9,
      "dayHigh": 1905.7,
      "dayLow": 1827.6,
      "change": 19.6,
      "changePercent": 1.06
    },
    "BHARTIARTL": {
      "symbol": "BHARTIARTL",
      "price": 1904.4,
      "previousClose": 1913.5,
      "open": 1904.4,
      "dayHigh": 1914,
      "dayLow": 1897.7,
      "change": -9.1,
      "changePercent": -0.48
    },
    "BHEL": {
      "symbol": "BHEL",
      "price": 402,
      "previousClose": 401.1,
      "open": 402,
      "dayHigh": 404,
      "dayLow": 396,
      "change": 0.9,
      "changePercent": 0.22
    },
    "BIOCON": {
      "symbol": "BIOCON",
      "price": 433.6,
      "previousClose": 428.15,
      "open": 433.6,
      "dayHigh": 434.55,
      "dayLow": 425.2,
      "change": 5.45,
      "changePercent": 1.27
    },
    "BPCL": {
      "symbol": "BPCL",
      "price": 290.8,
      "previousClose": 286.45,
      "open": 290.8,
      "dayHigh": 292.9,
      "dayLow": 280.05,
      "change": 4.35,
      "changePercent": 1.52
    },
    "BRITANNIA": {
      "symbol": "BRITANNIA",
      "price": 5344.5,
      "previousClose": 5416.5,
      "open": 5344.5,
      "dayHigh": 5390.5,
      "dayLow": 5321.5,
      "change": -72,
      "changePercent": -1.33
    },
    "CANBK": {
      "symbol": "CANBK",
      "price": 126,
      "previousClose": 126.15,
      "open": 126,
      "dayHigh": 126.57,
      "dayLow": 123.67,
      "change": -0.15,
      "changePercent": -0.12
    },
    "CAPACITE": {
      "symbol": "CAPACITE",
      "price": 222.5,
      "previousClose": 225.1,
      "open": 222.5,
      "dayHigh": 226.65,
      "dayLow": 220.95,
      "change": -2.6,
      "changePercent": -1.16
    },
    "CDSL": {
      "symbol": "CDSL",
      "price": 1208.5,
      "previousClose": 1209.5,
      "open": 1208.5,
      "dayHigh": 1209.8,
      "dayLow": 1192,
      "change": -1,
      "changePercent": -0.08
    },
    "CHOLAFIN": {
      "symbol": "CHOLAFIN",
      "price": 1512.5,
      "previousClose": 1511.4,
      "open": 1512.5,
      "dayHigh": 1514.8,
      "dayLow": 1491,
      "change": 1.1,
      "changePercent": 0.07
    },
    "CIPLA": {
      "symbol": "CIPLA",
      "price": 1408.4,
      "previousClose": 1409.8,
      "open": 1408.4,
      "dayHigh": 1422.1,
      "dayLow": 1392.3,
      "change": -1.4,
      "changePercent": -0.1
    },
    "COALINDIA": {
      "symbol": "COALINDIA",
      "price": 459.2,
      "previousClose": 456.95,
      "open": 459.2,
      "dayHigh": 460.05,
      "dayLow": 452.7,
      "change": 2.25,
      "changePercent": 0.49
    },
    "COCHINSHIP": {
      "symbol": "COCHINSHIP",
      "price": 1494.9,
      "previousClose": 1489.6,
      "open": 1494.9,
      "dayHigh": 1496.7,
      "dayLow": 1463.1,
      "change": 5.3,
      "changePercent": 0.36
    },
    "COFORGE": {
      "symbol": "COFORGE",
      "price": 1420.1,
      "previousClose": 1412,
      "open": 1420.1,
      "dayHigh": 1444.4,
      "dayLow": 1400,
      "change": 8.1,
      "changePercent": 0.57
    },
    "CROMPTON": {
      "symbol": "CROMPTON",
      "price": 290.4,
      "previousClose": 293.6,
      "open": 290.4,
      "dayHigh": 292.9,
      "dayLow": 287.15,
      "change": -3.2,
      "changePercent": -1.09
    },
    "CYIENT": {
      "symbol": "CYIENT",
      "price": 903.5,
      "previousClose": 905.85,
      "open": 903.5,
      "dayHigh": 914.4,
      "dayLow": 895,
      "change": -2.35,
      "changePercent": -0.26
    },
    "DBL": {
      "symbol": "DBL",
      "price": 439.4,
      "previousClose": 444.45,
      "open": 439.4,
      "dayHigh": 445.8,
      "dayLow": 435.9,
      "change": -5.05,
      "changePercent": -1.14
    },
    "DIVISLAB": {
      "symbol": "DIVISLAB",
      "price": 6907,
      "previousClose": 6912,
      "open": 6907,
      "dayHigh": 6960,
      "dayLow": 6800.5,
      "change": -5,
      "changePercent": -0.07
    },
    "DLF": {
      "symbol": "DLF",
      "price": 580.65,
      "previousClose": 577.4,
      "open": 580.65,
      "dayHigh": 582,
      "dayLow": 565.2,
      "change": 3.25,
      "changePercent": 0.56
    },
    "DMART": {
      "symbol": "DMART",
      "price": 4138,
      "previousClose": 4236,
      "open": 4138,
      "dayHigh": 4240.2,
      "dayLow": 4111,
      "change": -98,
      "changePercent": -2.31
    },
    "DRREDDY": {
      "symbol": "DRREDDY",
      "price": 1328.7,
      "previousClose": 1335.2,
      "open": 1328.7,
      "dayHigh": 1336,
      "dayLow": 1322.3,
      "change": -6.5,
      "changePercent": -0.49
    },
    "EICHERMOT": {
      "symbol": "EICHERMOT",
      "price": 6887,
      "previousClose": 6882.5,
      "open": 6887,
      "dayHigh": 6890,
      "dayLow": 6752.5,
      "change": 4.5,
      "changePercent": 0.07
    },
    "FEDERALBNK": {
      "symbol": "FEDERALBNK",
      "price": 287.35,
      "previousClose": 286.6,
      "open": 287.35,
      "dayHigh": 287.9,
      "dayLow": 283.1,
      "change": 0.75,
      "changePercent": 0.26
    },
    "FINCABLES": {
      "symbol": "FINCABLES",
      "price": 1038.35,
      "previousClose": 1056.25,
      "open": 1038.35,
      "dayHigh": 1048.3,
      "dayLow": 1024.4,
      "change": -17.9,
      "changePercent": -1.69
    },
    "FORTIS": {
      "symbol": "FORTIS",
      "price": 970.55,
      "previousClose": 960.55,
      "open": 970.55,
      "dayHigh": 972,
      "dayLow": 952,
      "change": 10,
      "changePercent": 1.04
    },
    "GLOBALVECT": {
      "symbol": "GLOBALVECT",
      "price": 167.58,
      "previousClose": 165.12,
      "open": 167.58,
      "dayHigh": 169.78,
      "dayLow": 161.2,
      "change": 2.46,
      "changePercent": 1.49
    },
    "GODREJPROP": {
      "symbol": "GODREJPROP",
      "price": 1719.8,
      "previousClose": 1715.4,
      "open": 1719.8,
      "dayHigh": 1723.4,
      "dayLow": 1676.3,
      "change": 4.4,
      "changePercent": 0.26
    },
    "GRAPHITE": {
      "symbol": "GRAPHITE",
      "price": 734,
      "previousClose": 748,
      "open": 734,
      "dayHigh": 747.3,
      "dayLow": 727.45,
      "change": -14,
      "changePercent": -1.87
    },
    "GRASIM": {
      "symbol": "GRASIM",
      "price": 2910.2,
      "previousClose": 2935.2,
      "open": 2910.2,
      "dayHigh": 2922,
      "dayLow": 2880.6,
      "change": -25,
      "changePercent": -0.85
    },
    "GRAUWEIL": {
      "symbol": "GRAUWEIL",
      "price": 65.17,
      "previousClose": 64.61,
      "open": 65.17,
      "dayHigh": 66.04,
      "dayLow": 64.3,
      "change": 0.56,
      "changePercent": 0.87
    },
    "GRSE": {
      "symbol": "GRSE",
      "price": 2628,
      "previousClose": 2658.5,
      "open": 2628,
      "dayHigh": 2648.9,
      "dayLow": 2587,
      "change": -30.5,
      "changePercent": -1.15
    },
    "HAL": {
      "symbol": "HAL",
      "price": 4308,
      "previousClose": 4333.2,
      "open": 4308,
      "dayHigh": 4317.4,
      "dayLow": 4251.1,
      "change": -25.2,
      "changePercent": -0.58
    },
    "HAVELLS": {
      "symbol": "HAVELLS",
      "price": 1210.8,
      "previousClose": 1207.2,
      "open": 1210.8,
      "dayHigh": 1212.5,
      "dayLow": 1190.5,
      "change": 3.6,
      "changePercent": 0.3
    },
    "HBLPOWER": {
      "symbol": "HBLPOWER",
      "price": 758.75,
      "previousClose": 752.2,
      "open": 758.75,
      "dayHigh": 762,
      "dayLow": 741.3,
      "change": 6.55,
      "changePercent": 0.87
    },
    "HCLTECH": {
      "symbol": "HCLTECH",
      "price": 1170.9,
      "previousClose": 1179.4,
      "open": 1170.9,
      "dayHigh": 1181,
      "dayLow": 1162.4,
      "change": -8.5,
      "changePercent": -0.72
    },
    "HDFCBANK": {
      "symbol": "HDFCBANK",
      "price": 760.05,
      "previousClose": 762.45,
      "open": 760.05,
      "dayHigh": 762.25,
      "dayLow": 755.15,
      "change": -2.4,
      "changePercent": -0.31
    },
    "HEROMOTOCO": {
      "symbol": "HEROMOTOCO",
      "price": 4970,
      "previousClose": 5007.5,
      "open": 4970,
      "dayHigh": 5015,
      "dayLow": 4902,
      "change": -37.5,
      "changePercent": -0.75
    },
    "HINDALCO": {
      "symbol": "HINDALCO",
      "price": 1078.8,
      "previousClose": 1048.3,
      "open": 1078.8,
      "dayHigh": 1090,
      "dayLow": 1038.4,
      "change": 30.5,
      "changePercent": 2.91
    },
    "HINDUNILVR": {
      "symbol": "HINDUNILVR",
      "price": 2219.3,
      "previousClose": 2232.9,
      "open": 2219.3,
      "dayHigh": 2226.9,
      "dayLow": 2201,
      "change": -13.6,
      "changePercent": -0.61
    },
    "ICICIBANK": {
      "symbol": "ICICIBANK",
      "price": 1231.5,
      "previousClose": 1240.8,
      "open": 1231.5,
      "dayHigh": 1236,
      "dayLow": 1223.3,
      "change": -9.3,
      "changePercent": -0.75
    },
    "IDFCFIRSTB": {
      "symbol": "IDFCFIRSTB",
      "price": 67.59,
      "previousClose": 67.81,
      "open": 67.59,
      "dayHigh": 67.92,
      "dayLow": 66.72,
      "change": -0.22,
      "changePercent": -0.32
    },
    "INDIANB": {
      "symbol": "INDIANB",
      "price": 811.7,
      "previousClose": 817.1,
      "open": 811.7,
      "dayHigh": 818.4,
      "dayLow": 803.55,
      "change": -5.4,
      "changePercent": -0.66
    },
    "INDUSINDBK": {
      "symbol": "INDUSINDBK",
      "price": 887.9,
      "previousClose": 895.25,
      "open": 887.9,
      "dayHigh": 893.4,
      "dayLow": 881.15,
      "change": -7.35,
      "changePercent": -0.82
    },
    "INDUSTOWER": {
      "symbol": "INDUSTOWER",
      "price": 427.15,
      "previousClose": 430.7,
      "open": 427.15,
      "dayHigh": 431,
      "dayLow": 424.25,
      "change": -3.55,
      "changePercent": -0.82
    },
    "INFY": {
      "symbol": "INFY",
      "price": 1195,
      "previousClose": 1196.9,
      "open": 1195,
      "dayHigh": 1206.9,
      "dayLow": 1184.9,
      "change": -1.9,
      "changePercent": -0.16
    },
    "IRCTC": {
      "symbol": "IRCTC",
      "price": 526.8,
      "previousClose": 529.8,
      "open": 526.8,
      "dayHigh": 530.7,
      "dayLow": 525.2,
      "change": -3,
      "changePercent": -0.57
    },
    "IREDA": {
      "symbol": "IREDA",
      "price": 126.3,
      "previousClose": 127.77,
      "open": 126.3,
      "dayHigh": 127.45,
      "dayLow": 125.72,
      "change": -1.47,
      "changePercent": -1.15
    },
    "ITC": {
      "symbol": "ITC",
      "price": 307,
      "previousClose": 310.3,
      "open": 307,
      "dayHigh": 309.65,
      "dayLow": 306.2,
      "change": -3.3,
      "changePercent": -1.06
    },
    "JINDALSTEL": {
      "symbol": "JINDALSTEL",
      "price": 1214.8,
      "previousClose": 1226.3,
      "open": 1214.8,
      "dayHigh": 1217.8,
      "dayLow": 1200.9,
      "change": -11.5,
      "changePercent": -0.94
    },
    "JKTYRE": {
      "symbol": "JKTYRE",
      "price": 359.35,
      "previousClose": 368.6,
      "open": 359.35,
      "dayHigh": 369.05,
      "dayLow": 357.7,
      "change": -9.25,
      "changePercent": -2.51
    },
    "JSWSTEEL": {
      "symbol": "JSWSTEEL",
      "price": 1278.5,
      "previousClose": 1285.2,
      "open": 1278.5,
      "dayHigh": 1280,
      "dayLow": 1261.5,
      "change": -6.7,
      "changePercent": -0.52
    },
    "KOTAKBANK": {
      "symbol": "KOTAKBANK",
      "price": 382.35,
      "previousClose": 381.95,
      "open": 382.35,
      "dayHigh": 383.5,
      "dayLow": 376.3,
      "change": 0.4,
      "changePercent": 0.1
    },
    "KPITTECH": {
      "symbol": "KPITTECH",
      "price": 751.9,
      "previousClose": 743.7,
      "open": 751.9,
      "dayHigh": 760.9,
      "dayLow": 741.5,
      "change": 8.2,
      "changePercent": 1.1
    },
    "LICHSGFIN": {
      "symbol": "LICHSGFIN",
      "price": 539.2,
      "previousClose": 543,
      "open": 539.2,
      "dayHigh": 543.5,
      "dayLow": 535.3,
      "change": -3.8,
      "changePercent": -0.7
    },
    "LT": {
      "symbol": "LT",
      "price": 3909,
      "previousClose": 3921,
      "open": 3909,
      "dayHigh": 3943.5,
      "dayLow": 3883.1,
      "change": -12,
      "changePercent": -0.31
    },
    "LUPIN": {
      "symbol": "LUPIN",
      "price": 2289,
      "previousClose": 2287.4,
      "open": 2289,
      "dayHigh": 2309.6,
      "dayLow": 2264.8,
      "change": 1.6,
      "changePercent": 0.07
    },
    "M&M": {
      "symbol": "M&M",
      "price": 3128.3,
      "previousClose": 3092.3,
      "open": 3128.3,
      "dayHigh": 3134,
      "dayLow": 3033,
      "change": 36,
      "changePercent": 1.16
    },
    "MANAPPURAM": {
      "symbol": "MANAPPURAM",
      "price": 318.4,
      "previousClose": 315.3,
      "open": 318.4,
      "dayHigh": 323.8,
      "dayLow": 311.4,
      "change": 3.1,
      "changePercent": 0.98
    },
    "MARUTI": {
      "symbol": "MARUTI",
      "price": 13044,
      "previousClose": 12956,
      "open": 13044,
      "dayHigh": 13057,
      "dayLow": 12753,
      "change": 88,
      "changePercent": 0.68
    },
    "MAXHEALTH": {
      "symbol": "MAXHEALTH",
      "price": 1075.45,
      "previousClose": 1068.75,
      "open": 1075.45,
      "dayHigh": 1078,
      "dayLow": 1052.75,
      "change": 6.7,
      "changePercent": 0.63
    },
    "METROPOLIS": {
      "symbol": "METROPOLIS",
      "price": 507.85,
      "previousClose": 508.4,
      "open": 507.85,
      "dayHigh": 512.85,
      "dayLow": 495.7,
      "change": -0.55,
      "changePercent": -0.11
    },
    "MPHASIS": {
      "symbol": "MPHASIS",
      "price": 2230.1,
      "previousClose": 2220.5,
      "open": 2230.1,
      "dayHigh": 2242,
      "dayLow": 2175.2,
      "change": 9.6,
      "changePercent": 0.43
    },
    "MUTHOOTFIN": {
      "symbol": "MUTHOOTFIN",
      "price": 3304.1,
      "previousClose": 3303.6,
      "open": 3304.1,
      "dayHigh": 3308.8,
      "dayLow": 3236,
      "change": 0.5,
      "changePercent": 0.02
    },
    "NATCOPHARM": {
      "symbol": "NATCOPHARM",
      "price": 1157.6,
      "previousClose": 1130.9,
      "open": 1157.6,
      "dayHigh": 1163.9,
      "dayLow": 1130.9,
      "change": 26.7,
      "changePercent": 2.36
    },
    "NATIONALUM": {
      "symbol": "NATIONALUM",
      "price": 402.15,
      "previousClose": 398.95,
      "open": 402.15,
      "dayHigh": 402.6,
      "dayLow": 393.2,
      "change": 3.2,
      "changePercent": 0.8
    },
    "NESTLEIND": {
      "symbol": "NESTLEIND",
      "price": 1418.5,
      "previousClose": 1431.4,
      "open": 1418.5,
      "dayHigh": 1426.9,
      "dayLow": 1398.5,
      "change": -12.9,
      "changePercent": -0.9
    },
    "NHPC": {
      "symbol": "NHPC",
      "price": 79.26,
      "previousClose": 79.06,
      "open": 79.26,
      "dayHigh": 79.35,
      "dayLow": 77.93,
      "change": 0.2,
      "changePercent": 0.25
    },
    "NTPC": {
      "symbol": "NTPC",
      "price": 392,
      "previousClose": 389.4,
      "open": 392,
      "dayHigh": 392.4,
      "dayLow": 384,
      "change": 2.6,
      "changePercent": 0.67
    },
    "OBEROIRLTY": {
      "symbol": "OBEROIRLTY",
      "price": 1624.2,
      "previousClose": 1622,
      "open": 1624.2,
      "dayHigh": 1644.8,
      "dayLow": 1596.5,
      "change": 2.2,
      "changePercent": 0.14
    },
    "ONGC": {
      "symbol": "ONGC",
      "price": 298.5,
      "previousClose": 296.5,
      "open": 298.5,
      "dayHigh": 301.75,
      "dayLow": 293.85,
      "change": 2,
      "changePercent": 0.67
    },
    "PAGEIND": {
      "symbol": "PAGEIND",
      "price": 38285,
      "previousClose": 38700,
      "open": 38285,
      "dayHigh": 38700,
      "dayLow": 38020,
      "change": -415,
      "changePercent": -1.07
    },
    "PERSISTENT": {
      "symbol": "PERSISTENT",
      "price": 5123,
      "previousClose": 5066.3,
      "open": 5123,
      "dayHigh": 5149,
      "dayLow": 4986.3,
      "change": 56.7,
      "changePercent": 1.12
    },
    "PFC": {
      "symbol": "PFC",
      "price": 425.65,
      "previousClose": 431.6,
      "open": 425.65,
      "dayHigh": 430,
      "dayLow": 422.35,
      "change": -5.95,
      "changePercent": -1.38
    },
    "PIDILITIND": {
      "symbol": "PIDILITIND",
      "price": 1456.5,
      "previousClose": 1455.8,
      "open": 1456.5,
      "dayHigh": 1458.8,
      "dayLow": 1431.4,
      "change": 0.7,
      "changePercent": 0.05
    },
    "PNB": {
      "symbol": "PNB",
      "price": 101.5,
      "previousClose": 101.3,
      "open": 101.5,
      "dayHigh": 102.38,
      "dayLow": 99.67,
      "change": 0.2,
      "changePercent": 0.2
    },
    "POLYCAB": {
      "symbol": "POLYCAB",
      "price": 9223,
      "previousClose": 9162.5,
      "open": 9223,
      "dayHigh": 9238,
      "dayLow": 9016.5,
      "change": 60.5,
      "changePercent": 0.66
    },
    "POWERGRID": {
      "symbol": "POWERGRID",
      "price": 298.65,
      "previousClose": 298.6,
      "open": 298.65,
      "dayHigh": 298.95,
      "dayLow": 294.55,
      "change": 0.05,
      "changePercent": 0.02
    },
    "PRESTIGE": {
      "symbol": "PRESTIGE",
      "price": 1389.7,
      "previousClose": 1377.1,
      "open": 1389.7,
      "dayHigh": 1392.1,
      "dayLow": 1340.6,
      "change": 12.6,
      "changePercent": 0.91
    },
    "RECLTD": {
      "symbol": "RECLTD",
      "price": 331.75,
      "previousClose": 334.25,
      "open": 331.75,
      "dayHigh": 333.4,
      "dayLow": 328.15,
      "change": -2.5,
      "changePercent": -0.75
    },
    "RELIANCE": {
      "symbol": "RELIANCE",
      "price": 1356.3,
      "previousClose": 1322.7,
      "open": 1356.3,
      "dayHigh": 1358.3,
      "dayLow": 1312.6,
      "change": 33.6,
      "changePercent": 2.54
    },
    "SAMMAANCAP": {
      "symbol": "SAMMAANCAP",
      "price": 139.26,
      "previousClose": 138.25,
      "open": 139.26,
      "dayHigh": 140.85,
      "dayLow": 134.75,
      "change": 1.01,
      "changePercent": 0.73
    },
    "SBICARD": {
      "symbol": "SBICARD",
      "price": 621.5,
      "previousClose": 623.8,
      "open": 621.5,
      "dayHigh": 622.3,
      "dayLow": 614.6,
      "change": -2.3,
      "changePercent": -0.37
    },
    "SBILIFE": {
      "symbol": "SBILIFE",
      "price": 1874.7,
      "previousClose": 1881.4,
      "open": 1874.7,
      "dayHigh": 1882.4,
      "dayLow": 1860,
      "change": -6.7,
      "changePercent": -0.36
    },
    "SBIN": {
      "symbol": "SBIN",
      "price": 950.3,
      "previousClose": 948.8,
      "open": 950.3,
      "dayHigh": 950.7,
      "dayLow": 935,
      "change": 1.5,
      "changePercent": 0.16
    },
    "SHRIRAMFIN": {
      "symbol": "SHRIRAMFIN",
      "price": 917.6,
      "previousClose": 927.35,
      "open": 917.6,
      "dayHigh": 925.45,
      "dayLow": 913,
      "change": -9.75,
      "changePercent": -1.05
    },
    "SUNPHARMA": {
      "symbol": "SUNPHARMA",
      "price": 1878.1,
      "previousClose": 1882.3,
      "open": 1878.1,
      "dayHigh": 1892.9,
      "dayLow": 1872,
      "change": -4.2,
      "changePercent": -0.22
    },
    "SUZLON": {
      "symbol": "SUZLON",
      "price": 52.23,
      "previousClose": 52.91,
      "open": 52.23,
      "dayHigh": 52.65,
      "dayLow": 52,
      "change": -0.68,
      "changePercent": -1.29
    },
    "TATACHEM": {
      "symbol": "TATACHEM",
      "price": 729,
      "previousClose": 736.2,
      "open": 729,
      "dayHigh": 734.45,
      "dayLow": 726,
      "change": -7.2,
      "changePercent": -0.98
    },
    "TATACOMM": {
      "symbol": "TATACOMM",
      "price": 1766,
      "previousClose": 1646.6,
      "open": 1766,
      "dayHigh": 1784.8,
      "dayLow": 1630.2,
      "change": 119.4,
      "changePercent": 7.25
    },
    "TATAELXSI": {
      "symbol": "TATAELXSI",
      "price": 4168,
      "previousClose": 4186.1,
      "open": 4168,
      "dayHigh": 4196.9,
      "dayLow": 4138.2,
      "change": -18.1,
      "changePercent": -0.43
    },
    "TATAPOWER": {
      "symbol": "TATAPOWER",
      "price": 412.05,
      "previousClose": 415,
      "open": 412.05,
      "dayHigh": 415.95,
      "dayLow": 409.75,
      "change": -2.95,
      "changePercent": -0.71
    },
    "TATASTEEL": {
      "symbol": "TATASTEEL",
      "price": 204.19,
      "previousClose": 209.29,
      "open": 204.19,
      "dayHigh": 207.5,
      "dayLow": 203.04,
      "change": -5.1,
      "changePercent": -2.44
    },
    "TCS": {
      "symbol": "TCS",
      "price": 2330,
      "previousClose": 2327.1,
      "open": 2330,
      "dayHigh": 2342,
      "dayLow": 2317.8,
      "change": 2.9,
      "changePercent": 0.12
    },
    "TECHM": {
      "symbol": "TECHM",
      "price": 1440.6,
      "previousClose": 1467.1,
      "open": 1440.6,
      "dayHigh": 1476.5,
      "dayLow": 1437.3,
      "change": -26.5,
      "changePercent": -1.81
    },
    "TITAN": {
      "symbol": "TITAN",
      "price": 4080.7,
      "previousClose": 4102,
      "open": 4080.7,
      "dayHigh": 4109.9,
      "dayLow": 4053,
      "change": -21.3,
      "changePercent": -0.52
    },
    "TMCV": {
      "symbol": "TMCV",
      "price": 376.95,
      "previousClose": 378.65,
      "open": 376.95,
      "dayHigh": 377.5,
      "dayLow": 370.8,
      "change": -1.7,
      "changePercent": -0.45
    },
    "TMPV": {
      "symbol": "TMPV",
      "price": 361.2,
      "previousClose": 361.2,
      "open": 361.2,
      "dayHigh": 365,
      "dayLow": 356.1,
      "change": 0,
      "changePercent": 0
    },
    "TRENT": {
      "symbol": "TRENT",
      "price": 4085.5,
      "previousClose": 4069.6,
      "open": 4085.5,
      "dayHigh": 4098,
      "dayLow": 4022,
      "change": 15.9,
      "changePercent": 0.39
    },
    "UJJIVANSFB": {
      "symbol": "UJJIVANSFB",
      "price": 53.23,
      "previousClose": 54.13,
      "open": 53.23,
      "dayHigh": 53.94,
      "dayLow": 53.02,
      "change": -0.9,
      "changePercent": -1.66
    },
    "ULTRACEMCO": {
      "symbol": "ULTRACEMCO",
      "price": 11372,
      "previousClose": 11368,
      "open": 11372,
      "dayHigh": 11410,
      "dayLow": 11211,
      "change": 4,
      "changePercent": 0.04
    },
    "UNITECH": {
      "symbol": "UNITECH",
      "price": 4.36,
      "previousClose": 4.2,
      "open": 4.36,
      "dayHigh": 4.44,
      "dayLow": 4.14,
      "change": 0.16,
      "changePercent": 3.81
    },
    "VEDL": {
      "symbol": "VEDL",
      "price": 335.75,
      "previousClose": 337.65,
      "open": 335.75,
      "dayHigh": 339.45,
      "dayLow": 331.45,
      "change": -1.9,
      "changePercent": -0.56
    },
    "VOLTAS": {
      "symbol": "VOLTAS",
      "price": 1292.9,
      "previousClose": 1302.6,
      "open": 1292.9,
      "dayHigh": 1300.6,
      "dayLow": 1284.3,
      "change": -9.7,
      "changePercent": -0.74
    },
    "WHIRLPOOL": {
      "symbol": "WHIRLPOOL",
      "price": 852.3,
      "previousClose": 849.85,
      "open": 852.3,
      "dayHigh": 857.55,
      "dayLow": 832.8,
      "change": 2.45,
      "changePercent": 0.29
    },
    "WIPRO": {
      "symbol": "WIPRO",
      "price": 197.48,
      "previousClose": 195.17,
      "open": 197.48,
      "dayHigh": 197.5,
      "dayLow": 194.01,
      "change": 2.31,
      "changePercent": 1.18
    },
    "ZOMATO": {
      "symbol": "ZOMATO",
      "price": 244.94,
      "previousClose": 247.21,
      "open": 244.94,
      "dayHigh": 245.6,
      "dayLow": 242.3,
      "change": -2.27,
      "changePercent": -0.92
    },
    "ZYDUSLIFE": {
      "symbol": "ZYDUSLIFE",
      "price": 1049.1,
      "previousClose": 1018.9,
      "open": 1049.1,
      "dayHigh": 1093.65,
      "dayLow": 1043.75,
      "change": 30.2,
      "changePercent": 2.96
    }
  },
  "fetchedAt": "2026-05-20T08:37:04.380Z",
  "marketStatus": "open",
  "stats": {
    "total": 130,
    "success": 127,
    "failed": 3
  }
}